voicemaker/__init__.py
voicemaker/voicemaker.py
voicemaker-0.0.7.dist-info/LICENSE
voicemaker-0.0.7.dist-info/METADATA
voicemaker-0.0.7.dist-info/WHEEL
voicemaker-0.0.7.dist-info/top_level.txt
voicemaker-0.0.7.dist-info/RECORD
