Metadata-Version: 2.1
Name: voicemaker
Version: 0.0.7
Summary: A Voicemaker.in simple API interface
Home-page: https://github.com/IAL32/voicemaker-python
Author: Adrian Castro
Author-email: <adrian.d.castro.t@gmail.com>
License: MIT
Keywords: python,tts,voicemaker,api
Platform: UNKNOWN
Classifier: Development Status :: 3 - Alpha
Classifier: Intended Audience :: Education
Classifier: Programming Language :: Python :: 2
Classifier: Programming Language :: Python :: 3
Classifier: Operating System :: MacOS :: MacOS X
Classifier: Operating System :: Microsoft :: Windows
License-File: LICENSE
Requires-Dist: requests (>=2.2)
